ECTweaker.py
ECTweaker-2.3.dist-info/LICENSE
ECTweaker-2.3.dist-info/METADATA
ECTweaker-2.3.dist-info/WHEEL
ECTweaker-2.3.dist-info/top_level.txt
ECTweaker-2.3.dist-info/RECORD
