Metadata-Version: 2.1
Name: ECTweaker
Version: 2.3
Summary: ECTweaker Library for python allows users to read/write and control the EC of laptops, specially MSI!
Home-page: UNKNOWN
Author: Aditya Kumar Bajpai (YoCodingMonster)
License: UNKNOWN
Platform: UNKNOWN
Classifier: License :: OSI Approved :: MIT License
Classifier: Programming Language :: Python
Classifier: Programming Language :: Python :: 3
Classifier: Programming Language :: Python :: 3.6
Classifier: Programming Language :: Python :: 3.7
Classifier: Programming Language :: Python :: 3.8
Classifier: Programming Language :: Python :: 3.9
Classifier: Operating System :: POSIX :: Linux
License-File: LICENSE
